bulma/__init__.py
bulma/apps.py
bulma/management/__init__.py
bulma/management/commands/__init__.py
bulma/management/commands/bulma.py
bulma/management/commands/copy_bulma_static_into_project.py
bulma/static/bulma/css/style.css
bulma/static/bulma/css/style.css.map
bulma/static/bulma/css/style.min.css
bulma/static/bulma/sass/.gitignore
bulma/static/bulma/sass/package-lock.json
bulma/static/bulma/sass/package.json
bulma/static/bulma/sass/style.sass
bulma/templates/_layouts/one-column-center.html
bulma/templates/base.html
bulma/templates/bulma/base.html
bulma/templates/bulma/forms/bulma_field_include.html
bulma/templates/bulma/forms/bulma_horizontal_field_include.html
bulma/templates/bulma/forms/bulma_inline_field_include.html
bulma/templates/bulma/forms/field.html
bulma/templates/bulma/forms/field2.html
bulma/templates/bulma/forms/field_include.html
bulma/templates/bulma/forms/fields/basic_input.html
bulma/templates/bulma/forms/fields/checkbox.html
bulma/templates/bulma/forms/fields/checkbox_option_widget.html
bulma/templates/bulma/forms/fields/checkbox_select.html
bulma/templates/bulma/forms/fields/file.html
bulma/templates/bulma/forms/fields/inline_icon.html
bulma/templates/bulma/forms/fields/inline_icon_css.html
bulma/templates/bulma/forms/fields/input.html
bulma/templates/bulma/forms/fields/input_option.html
bulma/templates/bulma/forms/fields/radio.html
bulma/templates/bulma/forms/fields/select.html
bulma/templates/bulma/forms/fields/textarea.html
bulma/templates/bulma/forms/form.html
bulma/templates/bulma/forms/formset.html
bulma/templates/pagination.html
bulma/templates/registration/base.html
bulma/templates/registration/logged_out.html
bulma/templates/registration/login.html
bulma/templates/registration/password_change_done.html
bulma/templates/registration/password_change_form.html
bulma/templates/registration/password_reset_complete.html
bulma/templates/registration/password_reset_confirm.html
bulma/templates/registration/password_reset_done.html
django_bulma_form_templates-0.8.4.dist-info/LICENSE
django_bulma_form_templates-0.8.4.dist-info/WHEEL
django_bulma_form_templates-0.8.4.dist-info/METADATA
django_bulma_form_templates-0.8.4.dist-info/RECORD
